Metadata-Version: 1.0
Name: pymqo
Version: 0.1.0
Summary: Python Message Queue Object
Home-page: https://github.com/ducminhgd/pymqo
Author: Gia Duong Duc Minh
Author-email: giaduongducminh@gmail.com
License: UNKNOWN
Platform: UNKNOWN
